[{"fecha":"2012-1","indicativo":"1249I","p_max":"5.3(26)","n_cub":"11.0","hr":"81.0","n_gra":"0.0","n_fog":"10.0","inso":"3.5","q_max":"997.5(20)","nw_55":"1.0","q_mar":"1029.0","q_med":"987.8","tm_min":"4.6","ta_max":"16.5(03)","ts_min":"9.8","nt_30":"0.0","nv_0050":"0.0","n_des":"3.0","w_racha":"28/15.8(02)","np_100":"0.0","n_nub":"17.0","p_sol":"38.0","nw_91":"0.0","ts_20":"7.3","np_001":"16.0","ta_min":"0.4(11)","w_rec":"149.0","e":"89.0","np_300":"0.0","nv_1000":"4.0","evap":"365.0","p_mes":"30.5","n_llu":"17.0","n_tor":"0.0","w_med":"6.0","nt_00":"0.0","ti_max":"7.7","n_nie":"0.0","tm_mes":"8.1","tm_max":"11.7","nv_0100":"0.0","q_min":"974.9(15)","np_010":"11.0"},{"fecha":"2012-2","indicativo":"1249I","p_max":"39.0(05)","n_cub":"15.0","hr":"77.0","n_gra":"1.0","n_fog":"12.0","inso":"4.1","q_max":"999.3(04)","nw_55":"1.0","q_mar":"1030.0","q_med":"988.5","tm_min":"2.5","ta_max":"17.1(28)","ts_min":"8.1","nt_30":"0.0","nv_0050":"0.0","n_des":"2.0","w_racha":"02/16.1(05)","np_100":"5.0","n_nub":"12.0","p_sol":"38.0","nw_91":"0.0","ts_20":"6.2","np_001":"12.0","ta_min":"-1.6(04)","w_rec":"170.0","e":"75.0","np_300":"1.0","nv_1000":"5.0","evap":"383.0","p_mes":"120.9","n_llu":"9.0","n_tor":"0.0","w_med":"9.0","nt_00":"7.0","ti_max":"4.2","n_nie":"4.0","tm_mes":"6.2","tm_max":"9.8","nv_0100":"0.0","q_min":"976.9(01)","np_010":"11.0"},{"fecha":"2012-3","indicativo":"1249I","p_max":"8.6(18)","n_cub":"3.0","hr":"69.0","n_gra":"0.0","n_fog":"14.0","inso":"7.2","q_max":"995.9(19)","nw_55":"2.0","q_mar":"1026.0","q_med":"985.3","tm_min":"5.9","ta_max":"24.2(24)","ts_min":"12.4","nt_30":"0.0","nv_0050":"0.0","n_des":"4.0","w_racha":"26/17.5(18)","np_100":"0.0","n_nub":"24.0","p_sol":"60.0","nw_91":"0.0","ts_20":"11.3","np_001":"8.0","ta_min":"2.0(22)","w_rec":"168.0","e":"88.0","np_300":"0.0","nv_1000":"5.0","evap":"759.0","p_mes":"26.8","n_llu":"8.0","n_tor":"0.0","w_med":"8.0","nt_00":"0.0","ti_max":"9.4","n_nie":"0.0","tm_mes":"11.1","tm_max":"16.2","nv_0100":"0.0","q_min":"972.5(31)","np_010":"5.0"},{"fecha":"2012-4","indicativo":"1249I","p_max":"27.7(14)","n_cub":"23.0","hr":"79.0","n_gra":"2.0","n_fog":"5.0","inso":"3.1","q_max":"987.8(16)","nw_55":"4.0","q_mar":"1010.9","q_med":"970.6","tm_min":"6.1","ta_max":"19.6(25)","ts_min":"8.5","nt_30":"0.0","nv_0050":"0.0","n_des":"0.0","w_racha":"27/22.5(23)","np_100":"10.0","n_nub":"7.0","p_sol":"23.0","nw_91":"0.0","ts_20":"11.6","np_001":"27.0","ta_min":"3.5(15)","w_rec":"226.0","e":"92.0","np_300":"0.0","nv_1000":"3.0","evap":"523.0","p_mes":"218.0","n_llu":"25.0","n_tor":"1.0","w_med":"10.0","nt_00":"0.0","ti_max":"7.2","n_nie":"0.0","tm_mes":"9.5","tm_max":"12.8","nv_0100":"0.0","q_min":"954.3(25)","np_010":"20.0"},{"fecha":"2012-5","indicativo":"1249I","p_max":"12.2(19)","n_cub":"13.0","hr":"75.0","n_gra":"0.0","n_fog":"8.0","inso":"6.4","q_max":"990.6(12)","nw_55":"0.0","q_mar":"1016.1","q_med":"976.5","tm_min":"10.5","ta_max":"30.6(10)","ts_min":"15.1","nt_30":"1.0","nv_0050":"0.0","n_des":"3.0","w_racha":"12/13.6(02)","np_100":"1.0","n_nub":"15.0","p_sol":"43.0","nw_91":"0.0","ts_20":"16.7","np_001":"13.0","ta_min":"6.8(01)","w_rec":"172.0","e":"133.0","np_300":"0.0","nv_1000":"5.0","evap":"780.0","p_mes":"32.2","n_llu":"15.0","n_tor":"0.0","w_med":"8.0","nt_00":"0.0","ti_max":"13.8","n_nie":"0.0","tm_mes":"15.2","tm_max":"19.9","nv_0100":"0.0","q_min":"964.7(04)","np_010":"9.0"},{"fecha":"2012-6","indicativo":"1249I","p_max":"13.8(27)","n_cub":"14.0","hr":"76.0","n_gra":"1.0","n_fog":"10.0","inso":"5.7","q_max":"986.2(22)","nw_55":"1.0","q_mar":"1016.3","q_med":"977.0","tm_min":"12.9","ta_max":"35.0(27)","ts_min":"18.4","nt_30":"1.0","nv_0050":"0.0","n_des":"2.0","w_racha":"27/15.3(11)","np_100":"3.0","n_nub":"14.0","p_sol":"37.0","nw_91":"0.0","ts_20":"19.6","np_001":"18.0","ta_min":"9.4(13)","w_rec":"176.0","e":"152.0","np_300":"0.0","nv_1000":"5.0","evap":"736.0","p_mes":"76.1","n_llu":"18.0","n_tor":"2.0","w_med":"8.0","nt_00":"0.0","ti_max":"13.6","n_nie":"0.0","tm_mes":"17.3","tm_max":"21.6","nv_0100":"0.0","q_min":"962.7(07)","np_010":"13.0"},{"fecha":"2012-7","indicativo":"1249I","p_max":"6.3(09)","n_cub":"13.0","hr":"76.0","n_gra":"0.0","n_fog":"8.0","inso":"6.0","q_max":"989.8(16)","nw_55":"1.0","q_mar":"1018.7","q_med":"979.4","tm_min":"13.7","ta_max":"31.1(26)","ts_min":"17.9","nt_30":"1.0","nv_0050":"0.0","n_des":"3.0","w_racha":"32/16.4(13)","np_100":"0.0","n_nub":"15.0","p_sol":"40.0","nw_91":"0.0","ts_20":"19.9","np_001":"12.0","ta_min":"10.5(01)","w_rec":"153.0","e":"159.0","np_300":"0.0","nv_1000":"6.0","evap":"755.0","p_mes":"28.7","n_llu":"13.0","n_tor":"1.0","w_med":"8.0","nt_00":"0.0","ti_max":"15.2","n_nie":"0.0","tm_mes":"18.0","tm_max":"22.4","nv_0100":"0.0","q_min":"972.2(13)","np_010":"8.0"},{"fecha":"2012-8","indicativo":"1249I","p_max":"8.5(04)","n_cub":"6.0","hr":"70.0","n_gra":"0.0","n_fog":"1.0","inso":"7.5","q_max":"991.3(31)","nw_55":"0.0","q_mar":"1017.3","q_med":"978.4","tm_min":"15.5","ta_max":"33.2(10)","ts_min":"18.9","nt_30":"4.0","nv_0050":"0.0","n_des":"5.0","w_racha":"30/14.7(15)","np_100":"0.0","n_nub":"20.0","p_sol":"54.0","nw_91":"0.0","ts_20":"21.4","np_001":"7.0","ta_min":"11.6(06)","w_rec":"167.0","e":"165.0","np_300":"0.0","nv_1000":"1.0","evap":"1065.0","p_mes":"19.5","n_llu":"9.0","n_tor":"0.0","w_med":"8.0","nt_00":"0.0","ti_max":"20.6","n_nie":"0.0","tm_mes":"20.4","tm_max":"25.3","nv_0100":"0.0","q_min":"963.4(15)","np_010":"4.0"},{"fecha":"2012-9","indicativo":"1249I","p_max":"10.5(09)","n_cub":"10.0","hr":"72.0","n_gra":"0.0","n_fog":"9.0","inso":"6.1","q_max":"990.1(01)","nw_55":"3.0","q_mar":"1017.1","q_med":"977.8","tm_min":"13.2","ta_max":"30.6(08)","ts_min":"17.4","nt_30":"1.0","nv_0050":"0.0","n_des":"0.0","w_racha":"23/16.7(25)","np_100":"1.0","n_nub":"20.0","p_sol":"48.0","nw_91":"0.0","ts_20":"18.8","np_001":"8.0","ta_min":"9.0(26)","w_rec":"185.0","e":"150.0","np_300":"0.0","nv_1000":"5.0","evap":"854.0","p_mes":"25.0","n_llu":"11.0","n_tor":"1.0","w_med":"9.0","nt_00":"0.0","ti_max":"17.8","n_nie":"0.0","tm_mes":"18.1","tm_max":"23.0","nv_0100":"0.0","q_min":"960.9(23)","np_010":"6.0"},{"fecha":"2012-10","indicativo":"1249I","p_max":"31.6(26)","n_cub":"12.0","hr":"75.0","n_gra":"0.0","n_fog":"7.0","inso":"5.4","q_max":"982.9(28)","nw_55":"1.0","q_mar":"1012.9","q_med":"973.3","tm_min":"10.0","ta_max":"27.6(07)","ts_min":"18.0","nt_30":"0.0","nv_0050":"0.0","n_des":"3.0","w_racha":"32/16.1(14)","np_100":"6.0","n_nub":"16.0","p_sol":"49.0","nw_91":"0.0","ts_20":"14.5","np_001":"16.0","ta_min":"2.6(29)","w_rec":"162.0","e":"125.0","np_300":"1.0","nv_1000":"1.0","evap":"572.0","p_mes":"118.4","n_llu":"17.0","n_tor":"0.0","w_med":"7.0","nt_00":"0.0","ti_max":"12.2","n_nie":"0.0","tm_mes":"14.6","tm_max":"19.2","nv_0100":"0.0","q_min":"955.5(31)","np_010":"12.0"},{"fecha":"2012-11","indicativo":"1249I","p_max":"37.8(17)","n_cub":"14.0","hr":"75.0","n_gra":"1.0","n_fog":"7.0","inso":"3.9","q_max":"989.0(06)","nw_55":"2.0","q_mar":"1014.8","q_med":"974.5","tm_min":"6.2","ta_max":"23.0(15)","ts_min":"12.0","nt_30":"0.0","nv_0050":"0.0","n_des":"0.0","w_racha":"27/18.3(01)","np_100":"5.0","n_nub":"16.0","p_sol":"39.0","nw_91":"0.0","ts_20":"9.5","np_001":"18.0","ta_min":"2.0(22)","w_rec":"192.0","e":"94.0","np_300":"2.0","nv_1000":"2.0","evap":"544.0","p_mes":"165.8","n_llu":"18.0","n_tor":"1.0","w_med":"9.0","nt_00":"0.0","ti_max":"7.0","n_nie":"0.0","tm_mes":"10.0","tm_max":"13.8","nv_0100":"0.0","q_min":"954.5(01)","np_010":"14.0"},{"fecha":"2012-12","indicativo":"1249I","p_max":"10.4(14)","n_cub":"7.0","hr":"71.0","n_gra":"0.0","n_fog":"2.0","inso":"3.8","q_max":"990.9(27)","nw_55":"5.0","q_mar":"1019.0","q_med":"978.5","tm_min":"6.1","ta_max":"20.7(23)","ts_min":"13.0","nt_30":"0.0","nv_0050":"0.0","n_des":"2.0","w_racha":"27/24.4(21)","np_100":"1.0","n_nub":"22.0","p_sol":"43.0","nw_91":"0.0","np_001":"16.0","ta_min":"1.0(09)","w_rec":"184.0","e":"86.0","np_300":"0.0","nv_1000":"1.0","evap":"767.0","p_mes":"43.9","n_llu":"17.0","n_tor":"0.0","w_med":"8.0","nt_00":"0.0","ti_max":"8.6","n_nie":"0.0","tm_mes":"9.8","tm_max":"13.5","nv_0100":"0.0","q_min":"954.3(14)","np_010":"10.0"},{"fecha":"2012-13","indicativo":"1249I","p_max":"39.0(05/feb)","n_cub":"141.0","hr":"75.0","n_gra":"5.0","n_fog":"93.0","inso":"5.2","q_max":"999.3(04/feb)","nw_55":"21.0","q_mar":"1019.0","q_med":"979.0","tm_min":"8.9","ta_max":"35.0(27/jun)","ts_min":"18.9","nt_30":"8.0","nv_0050":"0.0","n_des":"27.0","w_racha":"27/24.4(21/dic)","np_100":"32.0","n_nub":"198.0","p_sol":"43.0","nw_91":"0.0","np_001":"171.0","ta_min":"-1.6(04/feb)","w_rec":"175.0","e":"117.0","np_300":"4.0","nv_1000":"43.0","evap":"8103.0","p_mes":"905.8","n_llu":"177.0","n_tor":"6.0","w_med":"8.0","nt_00":"7.0","ti_max":"4.2","n_nie":"4.0","tm_mes":"13.2","tm_max":"17.4","nv_0100":"0.0","q_min":"954.3(25/abr)","np_010":"123.0"}]
