[ {
  "fecha" : "2016-1",
  "indicativo" : "5246",
  "p_max" : "29.2(04)",
  "hr" : "80.0",
  "inso" : "3.6",
  "q_max" : "945.0(31)",
  "q_mar" : "1024.0",
  "q_med" : "933.7",
  "tm_min" : "5.3",
  "ta_max" : "17.9(24)",
  "ts_min" : "10.5",
  "nt_30" : "0.0",
  "np_100" : "6.0",
  "p_sol" : "36.0",
  "np_001" : "16.0",
  "ta_min" : "-0.6(16)",
  "e" : "89.0",
  "np_300" : "0.0",
  "p_mes" : "121.8",
  "nt_00" : "1.0",
  "ti_max" : "6.6",
  "tm_mes" : "8.3",
  "tm_max" : "11.2",
  "q_min" : "917.7(05)",
  "np_010" : "12.0"
}, {
  "fecha" : "2016-2",
  "indicativo" : "5246",
  "p_max" : "24.8(13)",
  "hr" : "71.0",
  "inso" : "4.5",
  "q_max" : "943.7(04)",
  "q_mar" : "1021.2",
  "q_med" : "931.0",
  "tm_min" : "4.4",
  "ta_max" : "17.8(01)",
  "ts_min" : "10.8",
  "nt_30" : "0.0",
  "np_100" : "4.0",
  "p_sol" : "42.0",
  "np_001" : "12.0",
  "ta_min" : "-2.3(17)",
  "e" : "77.0",
  "np_300" : "0.0",
  "p_mes" : "105.4",
  "nt_00" : "3.0",
  "ti_max" : "5.4",
  "tm_mes" : "8.0",
  "tm_max" : "11.5",
  "q_min" : "910.4(27)",
  "np_010" : "10.0"
}, {
  "fecha" : "2016-3",
  "indicativo" : "5246",
  "p_max" : "7.8(07)",
  "hr" : "61.0",
  "inso" : "6.7",
  "q_max" : "938.3(01)",
  "q_mar" : "1016.9",
  "q_med" : "927.5",
  "tm_min" : "4.0",
  "ta_max" : "24.6(30)",
  "ts_min" : "8.9",
  "nt_30" : "0.0",
  "np_100" : "0.0",
  "p_sol" : "55.0",
  "np_001" : "9.0",
  "ta_min" : "0.4(01)",
  "e" : "71.0",
  "np_300" : "0.0",
  "p_mes" : "34.8",
  "nt_00" : "0.0",
  "ti_max" : "6.2",
  "tm_mes" : "9.3",
  "tm_max" : "14.5",
  "q_min" : "917.4(07)",
  "np_010" : "6.0"
}, {
  "fecha" : "2016-4",
  "indicativo" : "5246",
  "hr" : "62.0",
  "inso" : "6.1",
  "q_max" : "933.7(21)",
  "q_mar" : "1013.6",
  "q_med" : "925.6",
  "tm_min" : "7.5",
  "ta_max" : "24.6(26)",
  "ts_min" : "11.3",
  "nt_30" : "0.0",
  "p_sol" : "46.0",
  "ta_min" : "2.7(01)",
  "e" : "90.0",
  "nt_00" : "0.0",
  "ti_max" : "10.1",
  "tm_mes" : "12.8",
  "tm_max" : "18.0",
  "q_min" : "913.9(04)"
}, {
  "fecha" : "2016-5",
  "indicativo" : "5246",
  "hr" : "54.0",
  "inso" : "6.6",
  "q_max" : "935.7(01)",
  "q_mar" : "1013.7",
  "q_med" : "927.0",
  "tm_min" : "10.7",
  "ta_max" : "30.1(20)",
  "ts_min" : "15.2",
  "nt_30" : "2.0",
  "p_sol" : "46.0",
  "ta_min" : "5.9(02)",
  "e" : "98.0",
  "nt_00" : "0.0",
  "ti_max" : "13.5",
  "tm_mes" : "16.7",
  "tm_max" : "22.7",
  "q_min" : "913.6(08)"
}, {
  "fecha" : "2016-6",
  "indicativo" : "5246",
  "hr" : "30.0",
  "inso" : "9.4",
  "q_max" : "937.6(19)",
  "q_mar" : "1013.1",
  "q_med" : "928.9",
  "tm_min" : "16.6",
  "ta_max" : "37.5(09)",
  "ts_min" : "21.5",
  "nt_30" : "23.0",
  "p_sol" : "64.0",
  "ta_min" : "10.3(16)",
  "e" : "89.0",
  "w_med" : "7.0",
  "nt_00" : "0.0",
  "ti_max" : "21.8",
  "tm_mes" : "24.6",
  "tm_max" : "32.6",
  "q_min" : "919.3(15)"
}, {
  "fecha" : "2016-7",
  "indicativo" : "5246",
  "p_max" : "0.6(07)",
  "hr" : "26.0",
  "inso" : "9.4",
  "q_max" : "934.2(08)",
  "nw_55" : "0.0",
  "q_mar" : "1012.8",
  "q_med" : "929.8",
  "tm_min" : "20.6",
  "ta_max" : "41.2(03)",
  "ts_min" : "24.8",
  "nt_30" : "31.0",
  "w_racha" : "13/13.9(20)",
  "np_100" : "0.0",
  "p_sol" : "65.0",
  "nw_91" : "0.0",
  "np_001" : "1.0",
  "ta_min" : "16.3(08)",
  "w_rec" : "176.0",
  "e" : "100.0",
  "np_300" : "0.0",
  "p_mes" : "0.6",
  "w_med" : "8.0",
  "nt_00" : "0.0",
  "ti_max" : "34.6",
  "tm_mes" : "29.3",
  "tm_max" : "37.9",
  "q_min" : "926.3(03)",
  "np_010" : "0.0"
}, {
  "fecha" : "2016-8",
  "indicativo" : "5246",
  "p_max" : "27.4(10)",
  "hr" : "28.0",
  "inso" : "10.3",
  "q_max" : "935.9(12)",
  "nw_55" : "0.0",
  "q_mar" : "1014.1",
  "q_med" : "930.7",
  "tm_min" : "20.0",
  "ta_max" : "39.6(02)",
  "ts_min" : "23.7",
  "nt_30" : "31.0",
  "w_racha" : "10/13.3(10)",
  "np_100" : "1.0",
  "p_sol" : "76.0",
  "nw_91" : "0.0",
  "np_001" : "3.0",
  "ta_min" : "15.6(10)",
  "w_rec" : "159.0",
  "e" : "101.0",
  "np_300" : "0.0",
  "p_mes" : "28.0",
  "w_med" : "7.0",
  "nt_00" : "0.0",
  "ti_max" : "32.0",
  "tm_mes" : "28.1",
  "tm_max" : "36.1",
  "q_min" : "924.7(18)",
  "np_010" : "1.0"
}, {
  "fecha" : "2016-9",
  "indicativo" : "5246",
  "w_med" : "7.0"
}, {
  "fecha" : "2016-10",
  "indicativo" : "5246"
}, {
  "fecha" : "2016-11",
  "indicativo" : "5246"
}, {
  "fecha" : "2016-12",
  "indicativo" : "5246",
  "p_max" : "19.0(14)",
  "hr" : "73.0",
  "inso" : "6.2",
  "q_max" : "946.5(24)",
  "nw_55" : "0.0",
  "q_mar" : "1026.5",
  "q_med" : "936.2",
  "tm_min" : "5.8",
  "ta_max" : "16.6(05)",
  "ts_min" : "9.8",
  "nt_30" : "0.0",
  "w_racha" : "02/14.2(17)",
  "np_100" : "1.0",
  "p_sol" : "65.0",
  "nw_91" : "0.0",
  "np_001" : "10.0",
  "ta_min" : "1.0(31)",
  "w_rec" : "179.0",
  "e" : "85.0",
  "np_300" : "0.0",
  "p_mes" : "36.8",
  "w_med" : "7.0",
  "nt_00" : "0.0",
  "ti_max" : "8.2",
  "tm_mes" : "9.3",
  "tm_max" : "12.8",
  "q_min" : "920.9(03)",
  "np_010" : "4.0"
}, {
  "fecha" : "2016-13",
  "indicativo" : "5246"
} ]
