[ {
  "fecha" : "2014-1",
  "indicativo" : "9987P",
  "hr" : "77.0",
  "nw_55" : "11.0",
  "tm_min" : "9.1",
  "ta_max" : "18.8(26)",
  "ts_min" : "14.2",
  "nt_30" : "0.0",
  "w_racha" : "27/28.9(05)",
  "nw_91" : "2.0",
  "ta_min" : "5.4(29)",
  "w_rec" : "279.0",
  "e" : "106.0",
  "w_med" : "10.0",
  "nt_00" : "0.0",
  "ti_max" : "11.5",
  "tm_mes" : "11.6",
  "tm_max" : "14.1"
}, {
  "fecha" : "2014-2",
  "indicativo" : "9987P",
  "hr" : "73.0",
  "nw_55" : "8.0",
  "tm_min" : "7.4",
  "ta_max" : "17.4(13)",
  "ts_min" : "10.4",
  "nt_30" : "0.0",
  "w_racha" : "29/30.0(10)",
  "nw_91" : "2.0",
  "ta_min" : "3.0(03)",
  "w_rec" : "248.0",
  "e" : "98.0",
  "w_med" : "11.0",
  "nt_00" : "0.0",
  "ti_max" : "11.5",
  "tm_mes" : "10.9",
  "tm_max" : "14.3"
}, {
  "fecha" : "2014-3",
  "indicativo" : "9987P",
  "p_max" : "2.0(12)",
  "hr" : "74.0",
  "nw_55" : "7.0",
  "tm_min" : "9.0",
  "ta_max" : "21.4(16)",
  "ts_min" : "13.1",
  "nt_30" : "0.0",
  "w_racha" : "25/38.6(25)",
  "np_100" : "0.0",
  "nw_91" : "2.0",
  "np_001" : "4.0",
  "ta_min" : "5.1(08)",
  "w_rec" : "257.0",
  "e" : "111.0",
  "np_300" : "0.0",
  "p_mes" : "3.5",
  "w_med" : "12.0",
  "nt_00" : "0.0",
  "ti_max" : "13.7",
  "tm_mes" : "12.9",
  "tm_max" : "16.7",
  "np_010" : "2.0"
}, {
  "fecha" : "2014-4",
  "indicativo" : "9987P",
  "p_max" : "17.9(03)",
  "hr" : "77.0",
  "nw_55" : "5.0",
  "tm_min" : "12.9",
  "ta_max" : "24.5(30)",
  "ts_min" : "16.1",
  "nt_30" : "0.0",
  "w_racha" : "28/23.6(25)",
  "np_100" : "1.0",
  "nw_91" : "0.0",
  "np_001" : "6.0",
  "ta_min" : "10.4(18)",
  "w_rec" : "225.0",
  "e" : "146.0",
  "np_300" : "0.0",
  "p_mes" : "28.5",
  "w_med" : "11.0",
  "nt_00" : "0.0",
  "ti_max" : "14.3",
  "tm_mes" : "16.3",
  "tm_max" : "19.7",
  "np_010" : "5.0"
}, {
  "fecha" : "2014-5",
  "indicativo" : "9987P",
  "p_max" : "7.5(24)",
  "hr" : "78.0",
  "nw_55" : "2.0",
  "tm_min" : "15.2",
  "ta_max" : "24.0(03)",
  "ts_min" : "17.8",
  "nt_30" : "0.0",
  "w_racha" : "31/18.6(02)",
  "np_100" : "0.0",
  "nw_91" : "0.0",
  "np_001" : "6.0",
  "ta_min" : "13.1(04)",
  "w_rec" : "261.0",
  "e" : "165.0",
  "np_300" : "0.0",
  "p_mes" : "13.7",
  "w_med" : "12.0",
  "nt_00" : "0.0",
  "ti_max" : "17.7",
  "tm_mes" : "18.1",
  "tm_max" : "20.8",
  "np_010" : "4.0"
}, {
  "fecha" : "2014-6",
  "indicativo" : "9987P",
  "p_max" : "8.7(24)",
  "hr" : "80.0",
  "nw_55" : "2.0",
  "tm_min" : "19.0",
  "ta_max" : "29.8(14)",
  "ts_min" : "21.4",
  "nt_30" : "0.0",
  "w_racha" : "18/19.2(17)",
  "np_100" : "0.0",
  "nw_91" : "0.0",
  "np_001" : "3.0",
  "ta_min" : "15.8(03)",
  "w_rec" : "168.0",
  "e" : "213.0",
  "np_300" : "0.0",
  "p_mes" : "11.1",
  "w_med" : "9.0",
  "nt_00" : "0.0",
  "ti_max" : "20.5",
  "tm_mes" : "21.8",
  "tm_max" : "24.6",
  "np_010" : "2.0"
}, {
  "fecha" : "2014-7",
  "indicativo" : "9987P"
}, {
  "fecha" : "2014-8",
  "indicativo" : "9987P",
  "e" : "256.0",
  "w_med" : "8.0"
}, {
  "fecha" : "2014-9",
  "indicativo" : "9987P",
  "w_med" : "5.0"
}, {
  "fecha" : "2014-10",
  "indicativo" : "9987P",
  "e" : "196.0",
  "w_med" : "6.0"
}, {
  "fecha" : "2014-11",
  "indicativo" : "9987P"
}, {
  "fecha" : "2014-12",
  "indicativo" : "9987P",
  "e" : "100.0",
  "w_med" : "14.0"
}, {
  "fecha" : "2014-13",
  "indicativo" : "9987P"
} ]
