[{"fecha":"2019-1","indicativo":"1083L","p_max":"33.5(22)","hr":"84.0","nw_55":"8.0","tm_min":"6.7","ta_max":"15.8(31)","ts_min":"10.0","nt_30":"0.0","w_racha":"32/25.0(27)","np_100":"9.0","nw_91":"0.0","np_001":"22.0","ta_min":"1.5(05)","w_rec":"343.0","e":"98.0","np_300":"1.0","p_mes":"205.1","w_med":"14.0","nt_00":"0.0","ti_max":"8.4","tm_mes":"9.0","tm_max":"11.2","np_010":"18.0"},{"fecha":"2019-2","indicativo":"1083L","p_max":"21.7(01)","hr":"73.0","nw_55":"7.0","tm_min":"7.4","ta_max":"25.9(26)","ts_min":"11.3","nt_30":"0.0","w_racha":"34/24.2(02)","np_100":"2.0","nw_91":"0.0","np_001":"9.0","ta_min":"2.7(04)","w_rec":"267.0","e":"99.0","np_300":"0.0","p_mes":"49.4","w_med":"11.0","nt_00":"0.0","ti_max":"9.9","tm_mes":"11.9","tm_max":"16.4","np_010":"6.0"},{"fecha":"2019-3","indicativo":"1083L","p_max":"15.7(07)","hr":"78.0","nw_55":"5.0","tm_min":"8.0","ta_max":"22.2(03)","ts_min":"10.2","nt_30":"0.0","w_racha":"24/22.2(06)","np_100":"2.0","nw_91":"0.0","np_001":"9.0","ta_min":"5.6(29)","w_rec":"244.0","e":"109.0","np_300":"0.0","p_mes":"58.0","w_med":"11.0","nt_00":"0.0","ti_max":"12.1","tm_mes":"11.9","tm_max":"15.7","np_010":"9.0"},{"fecha":"2019-4","indicativo":"1083L","p_max":"22.5(03)","hr":"80.0","nw_55":"7.0","tm_min":"8.9","ta_max":"24.2(15)","ts_min":"12.7","nt_30":"0.0","w_racha":"20/18.6(24)","np_100":"4.0","nw_91":"0.0","np_001":"15.0","ta_min":"3.8(03)","w_rec":"257.0","e":"123.0","np_300":"0.0","p_mes":"88.3","w_med":"11.0","nt_00":"0.0","ti_max":"10.5","tm_mes":"12.8","tm_max":"16.8","np_010":"11.0"},{"fecha":"2019-5","indicativo":"1083L","p_max":"23.3(18)","hr":"82.0","nw_55":"3.0","tm_min":"10.7","ta_max":"23.7(31)","ts_min":"13.7","nt_30":"0.0","w_racha":"27/19.2(18)","np_100":"2.0","nw_91":"0.0","np_001":"16.0","ta_min":"7.5(05)","w_rec":"293.0","e":"141.0","np_300":"0.0","p_mes":"79.3","w_med":"13.0","nt_00":"0.0","ti_max":"13.5","tm_mes":"14.3","tm_max":"17.8","np_010":"11.0"},{"fecha":"2019-6","indicativo":"1083L","p_max":"10.7(04)","hr":"83.0","nw_55":"2.0","tm_min":"13.8","ta_max":"30.7(26)","ts_min":"17.5","nt_30":"1.0","w_racha":"26/19.7(06)","np_100":"2.0","nw_91":"0.0","np_001":"9.0","ta_min":"10.3(10)","w_rec":"232.0","e":"173.0","np_300":"0.0","p_mes":"33.9","w_med":"11.0","nt_00":"0.0","ti_max":"15.6","tm_mes":"17.4","tm_max":"21.0","np_010":"6.0"},{"fecha":"2019-7","indicativo":"1083L","p_max":"10.4(26)","hr":"84.0","nw_55":"1.0","tm_min":"17.6","ta_max":"36.4(23)","ts_min":"20.9","nt_30":"1.0","w_racha":"27/16.1(09)","np_100":"1.0","nw_91":"0.0","np_001":"12.0","ta_min":"15.0(10)","w_rec":"211.0","e":"216.0","np_300":"0.0","p_mes":"29.8","w_med":"9.0","nt_00":"0.0","ti_max":"20.7","tm_mes":"20.9","tm_max":"24.1","np_010":"7.0"},{"fecha":"2019-8","indicativo":"1083L"},{"fecha":"2019-9","indicativo":"1083L","hr":"80.0","nw_55":"2.0","tm_min":"16.1","ta_max":"32.6(20)","ts_min":"18.4","nt_30":"1.0","w_racha":"30/17.8(10)","nw_91":"0.0","ta_min":"12.7(10)","w_rec":"211.0","e":"186.0","w_med":"8.0","nt_00":"0.0","ti_max":"18.6","tm_mes":"19.7","tm_max":"23.3"},{"fecha":"2019-10","indicativo":"1083L","hr":"80.0","nw_55":"7.0","tm_min":"13.9","ta_max":"28.2(26)","ts_min":"17.3","nt_30":"0.0","w_racha":"26/24.2(23)","nw_91":"0.0","ta_min":"9.8(22)","w_rec":"240.0","e":"159.0","w_med":"10.0","nt_00":"0.0","ti_max":"14.1","tm_mes":"17.5","tm_max":"21.0"},{"fecha":"2019-11","indicativo":"1083L","w_med":"18.0"},{"fecha":"2019-12","indicativo":"1083L","w_racha":"30/28.3(13)"},{"fecha":"2019-13","indicativo":"1083L"}]
