[{"fecha":"2018-1","indicativo":"3519X","p_max":"17.6(05)","hr":"74.0","nw_55":"0.0","tm_min":"4.6","ta_max":"18.0(21)","ts_min":"10.1","nt_30":"0.0","w_racha":"35/13.1(07)","np_100":"1.0","nw_91":"0.0","np_001":"8.0","ta_min":"0.2(15)","w_rec":"121.0","e":"85.0","np_300":"0.0","p_mes":"53.8","w_med":"5.0","nt_00":"0.0","ti_max":"5.4","tm_mes":"8.9","tm_max":"13.1","np_010":"6.0"},{"fecha":"2018-2","indicativo":"3519X","p_max":"27.0(28)","hr":"60.0","nw_55":"1.0","tm_min":"3.8","ta_max":"18.6(26)","ts_min":"9.5","nt_30":"0.0","w_racha":"05/17.8(05)","np_100":"2.0","nw_91":"0.0","np_001":"8.0","ta_min":"-0.3(22)","w_rec":"146.0","e":"69.0","np_300":"0.0","p_mes":"54.5","w_med":"7.0","nt_00":"5.0","ti_max":"7.4","tm_mes":"8.6","tm_max":"13.4","np_010":"3.0"},{"fecha":"2018-3","indicativo":"3519X","p_max":"42.1(09)","hr":"72.0","nw_55":"3.0","tm_min":"5.9","ta_max":"23.9(27)","ts_min":"10.0","nt_30":"0.0","w_racha":"26/20.3(11)","np_100":"7.0","nw_91":"0.0","np_001":"22.0","ta_min":"2.2(07)","w_rec":"191.0","e":"88.0","np_300":"1.0","p_mes":"216.5","w_med":"8.0","nt_00":"0.0","ti_max":"10.2","tm_mes":"10.1","tm_max":"14.3","np_010":"18.0"},{"fecha":"2018-4","indicativo":"3519X","p_max":"13.6(15)","hr":"67.0","nw_55":"1.0","tm_min":"9.3","ta_max":"29.4(25)","ts_min":"16.3","nt_30":"0.0","w_racha":"13/16.7(20)","np_100":"4.0","nw_91":"0.0","np_001":"16.0","ta_min":"4.1(11)","w_rec":"151.0","e":"109.0","np_300":"0.0","p_mes":"93.5","w_med":"7.0","nt_00":"0.0","ti_max":"9.3","tm_mes":"14.4","tm_max":"19.4","np_010":"12.0"},{"fecha":"2018-5","indicativo":"3519X","p_max":"10.9(25)","hr":"63.0","nw_55":"2.0","tm_min":"12.1","ta_max":"28.9(17)","ts_min":"16.2","nt_30":"0.0","w_racha":"12/19.4(07)","np_100":"1.0","nw_91":"0.0","np_001":"8.0","ta_min":"5.9(01)","w_rec":"117.0","e":"132.0","np_300":"0.0","p_mes":"29.2","w_med":"6.0","nt_00":"0.0","ti_max":"18.1","tm_mes":"18.0","tm_max":"23.9","np_010":"5.0"},{"fecha":"2018-6","indicativo":"3519X","p_max":"9.1(10)","hr":"57.0","nw_55":"0.0","tm_min":"16.8","ta_max":"38.4(24)","ts_min":"24.2","nt_30":"15.0","w_racha":"02/13.3(20)","np_100":"0.0","nw_91":"0.0","np_001":"9.0","ta_min":"10.3(04)","w_rec":"120.0","e":"159.0","np_300":"0.0","p_mes":"32.1","w_med":"5.0","nt_00":"0.0","ti_max":"19.5","tm_mes":"23.1","tm_max":"29.3","np_010":"7.0"},{"fecha":"2018-7","indicativo":"3519X","p_max":"0.0(--)","hr":"52.0","nw_55":"0.0","tm_min":"18.2","ta_max":"37.4(23)","ts_min":"23.0","nt_30":"27.0","w_racha":"36/10.8(31)","np_100":"0.0","nw_91":"0.0","np_001":"0.0","ta_min":"15.3(03)","w_rec":"109.0","e":"174.0","np_300":"0.0","p_mes":"0.0","w_med":"5.0","nt_00":"0.0","ti_max":"25.3","tm_mes":"25.7","tm_max":"33.2","np_010":"0.0"},{"fecha":"2018-8","indicativo":"3519X","p_max":"0.0(--)","hr":"43.0","nw_55":"1.0","tm_min":"21.9","ta_max":"43.5(03)","ts_min":"28.6","nt_30":"31.0","w_racha":"35/18.3(16)","np_100":"0.0","nw_91":"0.0","np_001":"0.0","ta_min":"16.7(29)","w_rec":"117.0","e":"185.0","np_300":"0.0","p_mes":"0.0","w_med":"5.0","nt_00":"0.0","ti_max":"32.6","tm_mes":"29.7","tm_max":"37.4","np_010":"0.0"},{"fecha":"2018-9","indicativo":"3519X","p_max":"7.6(08)","hr":"52.0","nw_55":"1.0","tm_min":"20.0","ta_max":"39.6(01)","ts_min":"25.7","nt_30":"27.0","w_racha":"09/21.7(08)","np_100":"0.0","nw_91":"0.0","np_001":"4.0","ta_min":"16.2(06)","w_rec":"106.0","e":"185.0","np_300":"0.0","p_mes":"10.3","w_med":"4.0","nt_00":"0.0","ti_max":"27.3","tm_mes":"26.9","tm_max":"33.6","np_010":"2.0"},{"fecha":"2018-10","indicativo":"3519X","p_max":"18.4(29)","hr":"63.0","nw_55":"2.0","tm_min":"12.6","ta_max":"31.7(04)","ts_min":"16.8","nt_30":"5.0","w_racha":"10/18.6(20)","np_100":"4.0","nw_91":"0.0","np_001":"14.0","ta_min":"3.5(29)","w_rec":"113.0","e":"128.0","np_300":"0.0","p_mes":"98.5","w_med":"5.0","nt_00":"0.0","ti_max":"11.2","tm_mes":"17.9","tm_max":"23.2","np_010":"10.0"},{"fecha":"2018-11","indicativo":"3519X","p_max":"21.5(04)","hr":"81.0","tm_min":"8.6","ta_max":"21.5(03)","ts_min":"12.7","nt_30":"0.0","np_100":"6.0","np_001":"21.0","ta_min":"3.9(28)","e":"113.0","np_300":"0.0","p_mes":"122.4","nt_00":"0.0","ti_max":"11.3","tm_mes":"11.9","tm_max":"15.2","np_010":"16.0"},{"fecha":"2018-12","indicativo":"3519X","p_max":"20.8(12)","hr":"79.0","nw_55":"0.0","tm_min":"5.1","ta_max":"18.9(05)","ts_min":"8.7","nt_30":"0.0","w_racha":"27/11.4(16)","np_100":"1.0","nw_91":"0.0","np_001":"9.0","ta_min":"1.2(29)","w_rec":"90.0","e":"92.0","np_300":"0.0","p_mes":"38.8","w_med":"4.0","nt_00":"0.0","ti_max":"7.7","tm_mes":"9.2","tm_max":"13.2","np_010":"4.0"},{"fecha":"2018-13","indicativo":"3519X","p_max":"42.1(09/mar)","hr":"64.0","tm_min":"11.6","ta_max":"43.5(03/ago)","ts_min":"28.6","nt_30":"105.0","np_100":"26.0","np_001":"119.0","ta_min":"-0.3(22/feb)","e":"127.0","np_300":"1.0","p_mes":"749.6","nt_00":"5.0","ti_max":"5.4","tm_mes":"17.0","tm_max":"22.4","np_010":"83.0"}]
