[{"fecha":"2014-1","indicativo":"5051X","w_racha":"30/32.8(27)"},{"fecha":"2014-2","indicativo":"5051X","hr":"70.0","q_max":"902.7(27)","q_mar":"1017.3","q_med":"891.4","tm_min":"1.1","ta_max":"19.1(14)","ts_min":"8.2","nt_30":"0.0","w_racha":"25/31.9(05)","ta_min":"-4.1(03)","e":"68.0","w_med":"12.0","nt_00":"12.0","ti_max":"6.8","tm_mes":"7.1","tm_max":"13.0","q_min":"876.4(09)"},{"fecha":"2014-3","indicativo":"5051X"},{"fecha":"2014-4","indicativo":"5051X"},{"fecha":"2014-5","indicativo":"5051X"},{"fecha":"2014-6","indicativo":"5051X"},{"fecha":"2014-7","indicativo":"5051X"},{"fecha":"2014-8","indicativo":"5051X","hr":"32.0","q_max":"898.4(23)","q_mar":"1011.5","q_med":"893.8","tm_min":"14.8","ta_max":"37.0(27)","ts_min":"18.1","nt_30":"28.0","ta_min":"12.0(03)","e":"93.0","nt_00":"0.0","ti_max":"30.9","tm_mes":"24.6","tm_max":"34.4","q_min":"889.0(01)"},{"fecha":"2014-9","indicativo":"5051X","hr":"48.0","q_max":"900.7(30)","q_mar":"1013.6","q_med":"893.8","tm_min":"12.6","ta_max":"38.0(03)","ts_min":"17.3","nt_30":"12.0","ta_min":"8.1(23)","e":"104.0","nt_00":"0.0","ti_max":"15.4","tm_mes":"20.8","tm_max":"28.9","q_min":"886.9(17)"},{"fecha":"2014-10","indicativo":"5051X"},{"fecha":"2014-11","indicativo":"5051X","hr":"67.0","q_max":"900.3(01)","q_mar":"1011.6","q_med":"888.0","tm_min":"4.8","ta_max":"24.5(01)","ts_min":"8.9","nt_30":"0.0","ta_min":"-0.7(10)","e":"84.0","nt_00":"3.0","ti_max":"10.3","tm_mes":"10.7","tm_max":"16.5","q_min":"865.3(28)"},{"fecha":"2014-12","indicativo":"5051X"},{"fecha":"2014-13","indicativo":"5051X"}]
