[{"fecha":"2014-1","indicativo":"5783","p_max":"23.6(17)","n_cub":"11.0","hr":"76.0","n_gra":"0.0","n_fog":"3.0","inso":"5.3","q_max":"1027.5(24)","nw_55":"1.0","q_mar":"1018.3","q_med":"1014.6","tm_min":"8.0","ta_max":"20.1(26)","ts_min":"14.7","nt_30":"0.0","nv_0050":"0.0","n_des":"4.0","w_racha":"28/23.6(04)","np_100":"2.0","n_nub":"15.0","p_sol":"53.0","nw_91":"0.0","np_001":"15.0","ta_min":"2.9(20)","w_rec":"243.0","e":"112.0","np_300":"0.0","nv_1000":"0.0","evap":"835.0","p_mes":"77.6","n_llu":"17.0","n_tor":"0.0","w_med":"11.0","nt_00":"0.0","ti_max":"11.8","n_nie":"0.0","tm_mes":"12.4","tm_max":"16.7","nv_0100":"0.0","q_min":"986.4(19)","np_010":"10.0"},{"fecha":"2014-2","indicativo":"5783","p_max":"24.2(09)","n_cub":"13.0","hr":"76.0","n_gra":"0.0","n_fog":"6.0","inso":"4.9","q_max":"1029.2(27)","nw_55":"7.0","q_mar":"1019.7","q_med":"1016.0","tm_min":"7.7","ta_max":"20.6(23)","ts_min":"15.1","nt_30":"0.0","nv_0050":"0.0","n_des":"1.0","w_racha":"27/27.8(09)","np_100":"2.0","n_nub":"14.0","p_sol":"45.0","nw_91":"1.0","np_001":"16.0","ta_min":"2.2(02)","w_rec":"283.0","e":"113.0","np_300":"0.0","nv_1000":"1.0","evap":"743.0","p_mes":"67.1","n_llu":"21.0","n_tor":"0.0","w_med":"12.0","nt_00":"0.0","ti_max":"14.5","n_nie":"0.0","tm_mes":"12.4","tm_max":"17.0","nv_0100":"0.0","q_min":"998.2(09)","np_010":"11.0"},{"fecha":"2014-3","indicativo":"5783","p_max":"24.1(28)","n_cub":"3.0","hr":"58.0","n_gra":"0.0","n_fog":"2.0","inso":"8.6","q_max":"1026.0(25)","nw_55":"1.0","q_mar":"1018.6","q_med":"1014.9","tm_min":"8.6","ta_max":"27.3(17)","ts_min":"14.0","nt_30":"0.0","nv_0050":"0.0","n_des":"9.0","w_racha":"26/16.4(01)","np_100":"1.0","n_nub":"19.0","p_sol":"72.0","nw_91":"0.0","np_001":"9.0","ta_min":"5.3(23)","w_rec":"281.0","e":"98.0","np_300":"0.0","nv_1000":"0.0","evap":"1713.0","p_mes":"39.5","n_llu":"10.0","n_tor":"0.0","w_med":"12.0","nt_00":"0.0","ti_max":"12.3","n_nie":"0.0","tm_mes":"15.1","tm_max":"21.6","nv_0100":"0.0","q_min":"999.1(29)","np_010":"3.0"},{"fecha":"2014-4","indicativo":"5783","p_max":"15.0(20)","n_cub":"4.0","hr":"60.0","n_gra":"0.0","n_fog":"1.0","inso":"9.1","q_max":"1022.6(25)","nw_55":"1.0","q_mar":"1015.3","q_med":"1011.7","tm_min":"12.7","ta_max":"32.6(17)","ts_min":"15.8","nt_30":"5.0","nv_0050":"0.0","n_des":"10.0","w_racha":"22/16.1(01)","np_100":"1.0","n_nub":"16.0","p_sol":"69.0","nw_91":"0.0","np_001":"7.0","ta_min":"7.4(04)","w_rec":"224.0","e":"133.0","np_300":"0.0","nv_1000":"1.0","evap":"1755.0","p_mes":"35.4","n_llu":"7.0","n_tor":"2.0","w_med":"10.0","nt_00":"0.0","ti_max":"17.4","n_nie":"0.0","tm_mes":"19.2","tm_max":"25.6","nv_0100":"0.0","q_min":"997.0(02)","np_010":"6.0"},{"fecha":"2014-5","indicativo":"5783","p_max":"6.3(20)","n_cub":"0.0","hr":"39.0","n_gra":"0.0","n_fog":"0.0","inso":"12.4","q_max":"1017.5(26)","nw_55":"2.0","q_mar":"1014.5","q_med":"1010.9","tm_min":"14.7","ta_max":"36.3(11)","ts_min":"18.5","nt_30":"20.0","nv_0050":"0.0","n_des":"16.0","w_racha":"22/18.1(21)","np_100":"0.0","n_nub":"15.0","p_sol":"87.0","nw_91":"0.0","np_001":"2.0","ta_min":"10.4(22)","w_rec":"242.0","e":"111.0","np_300":"0.0","nv_1000":"0.0","evap":"3073.0","p_mes":"7.3","n_llu":"2.0","n_tor":"0.0","w_med":"12.0","nt_00":"0.0","ti_max":"21.5","n_nie":"0.0","tm_mes":"22.5","tm_max":"30.3","nv_0100":"0.0","q_min":"1002.0(21)","np_010":"2.0"},{"fecha":"2014-6","indicativo":"5783","p_max":"1.5(23)","n_cub":"1.0","hr":"43.0","n_gra":"0.0","n_fog":"0.0","inso":"12.4","q_max":"1016.5(01)","nw_55":"0.0","q_mar":"1015.3","q_med":"1011.8","tm_min":"17.6","ta_max":"40.5(14)","ts_min":"21.7","nt_30":"19.0","nv_0050":"0.0","n_des":"14.0","w_racha":"26/14.4(23)","np_100":"0.0","n_nub":"15.0","p_sol":"84.0","nw_91":"0.0","np_001":"3.0","ta_min":"14.5(02)","w_rec":"276.0","e":"138.0","np_300":"0.0","nv_1000":"0.0","evap":"3105.0","p_mes":"1.7","n_llu":"3.0","n_tor":"1.0","w_med":"13.0","nt_00":"0.0","ti_max":"25.2","n_nie":"0.0","tm_mes":"24.7","tm_max":"31.7","nv_0100":"0.0","q_min":"1004.1(15)","np_010":"1.0"},{"fecha":"2014-7","indicativo":"5783","p_max":"0.0(--)","n_cub":"0.0","hr":"45.0","n_gra":"0.0","n_fog":"0.0","inso":"12.0","q_max":"1015.8(20)","nw_55":"0.0","q_mar":"1014.4","q_med":"1010.9","tm_min":"19.2","ta_max":"40.6(16)","ts_min":"22.8","nt_30":"25.0","nv_0050":"0.0","n_des":"16.0","w_racha":"22/13.9(02)","np_100":"0.0","n_nub":"15.0","p_sol":"83.0","nw_91":"0.0","np_001":"0.0","ta_min":"16.8(02)","w_rec":"284.0","e":"159.0","np_300":"0.0","nv_1000":"0.0","evap":"3195.0","p_mes":"0.0","n_llu":"0.0","n_tor":"0.0","w_med":"13.0","nt_00":"0.0","ti_max":"28.5","n_nie":"0.0","tm_mes":"26.6","tm_max":"34.0","nv_0100":"0.0","q_min":"1004.9(24)","np_010":"0.0"},{"fecha":"2014-8","indicativo":"5783","p_max":"0.0(--)","n_cub":"0.0","hr":"41.0","n_gra":"0.0","n_fog":"0.0","inso":"12.5","q_max":"1015.0(05)","nw_55":"0.0","q_mar":"1014.0","q_med":"1010.4","tm_min":"19.4","ta_max":"40.6(27)","ts_min":"23.5","nt_30":"30.0","nv_0050":"0.0","n_des":"27.0","w_racha":"09/14.4(17)","np_100":"0.0","n_nub":"4.0","p_sol":"92.0","nw_91":"0.0","np_001":"0.0","ta_min":"16.8(02)","w_rec":"233.0","e":"152.0","np_300":"0.0","nv_1000":"0.0","evap":"3208.0","p_mes":"0.0","n_llu":"0.0","n_tor":"0.0","w_med":"12.0","nt_00":"0.0","ti_max":"28.2","n_nie":"0.0","tm_mes":"27.6","tm_max":"35.7","nv_0100":"0.0","q_min":"1005.1(17)","np_010":"0.0"},{"fecha":"2014-9","indicativo":"5783","p_max":"63.2(27)","n_cub":"3.0","hr":"65.0","n_gra":"0.0","n_fog":"3.0","inso":"8.8","q_max":"1018.6(29)","nw_55":"3.0","q_mar":"1014.8","q_med":"1011.2","tm_min":"19.4","ta_max":"38.8(01)","ts_min":"21.9","nt_30":"14.0","nv_0050":"0.0","n_des":"5.0","w_racha":"99/16.9(16)","np_100":"3.0","n_nub":"22.0","p_sol":"71.0","nw_91":"0.0","np_001":"10.0","ta_min":"16.9(30)","w_rec":"227.0","e":"196.0","np_300":"1.0","nv_1000":"0.0","evap":"1569.0","p_mes":"127.6","n_llu":"11.0","n_tor":"2.0","w_med":"11.0","nt_00":"0.0","ti_max":"25.1","n_nie":"0.0","tm_mes":"24.6","tm_max":"29.8","nv_0100":"0.0","q_min":"1003.7(16)","np_010":"8.0"},{"fecha":"2014-10","indicativo":"5783","p_max":"48.5(09)","n_cub":"3.0","hr":"64.0","n_gra":"0.0","n_fog":"2.0","inso":"8.6","q_max":"1021.3(22)","nw_55":"0.0","q_mar":"1016.2","q_med":"1012.6","tm_min":"16.3","ta_max":"32.0(21)","ts_min":"20.7","nt_30":"11.0","nv_0050":"0.0","n_des":"7.0","w_racha":"25/15.0(12)","np_100":"3.0","n_nub":"21.0","p_sol":"77.0","nw_91":"0.0","np_001":"6.0","ta_min":"12.5(27)","w_rec":"204.0","e":"168.0","np_300":"1.0","nv_1000":"1.0","evap":"1731.0","p_mes":"102.5","n_llu":"8.0","n_tor":"2.0","w_med":"9.0","nt_00":"0.0","ti_max":"21.1","n_nie":"0.0","tm_mes":"22.2","tm_max":"28.0","nv_0100":"0.0","q_min":"1003.1(11)","np_010":"6.0"},{"fecha":"2014-11","indicativo":"5783","p_max":"42.1(27)","n_cub":"9.0","hr":"77.0","n_gra":"0.0","n_fog":"1.0","inso":"6.2","q_max":"1019.3(01)","nw_55":"3.0","q_mar":"1011.3","q_med":"1007.7","tm_min":"12.0","ta_max":"26.2(01)","ts_min":"17.1","nt_30":"0.0","nv_0050":"0.0","n_des":"3.0","w_racha":"21/17.5(04)","np_100":"4.0","n_nub":"18.0","p_sol":"61.0","nw_91":"0.0","np_001":"11.0","ta_min":"6.5(10)","w_rec":"232.0","e":"143.0","np_300":"2.0","nv_1000":"0.0","evap":"894.0","p_mes":"140.7","n_llu":"12.0","n_tor":"0.0","w_med":"10.0","nt_00":"0.0","ti_max":"15.3","n_nie":"0.0","tm_mes":"16.2","tm_max":"20.4","nv_0100":"0.0","q_min":"977.6(28)","np_010":"10.0"},{"fecha":"2014-12","indicativo":"5783","p_max":"29.5(13)","n_cub":"4.0","hr":"79.0","n_gra":"0.0","n_fog":"7.0","inso":"7.2","q_max":"1030.4(31)","nw_55":"2.0","q_mar":"1024.4","q_med":"1020.6","tm_min":"5.9","ta_max":"19.0(02)","ts_min":"11.7","nt_30":"0.0","nv_0050":"0.0","n_des":"14.0","w_racha":"17/17.5(13)","np_100":"1.0","n_nub":"13.0","p_sol":"75.0","nw_91":"0.0","np_001":"4.0","ta_min":"2.5(31)","w_rec":"185.0","e":"104.0","np_300":"0.0","nv_1000":"3.0","evap":"714.0","p_mes":"35.1","n_llu":"4.0","n_tor":"0.0","w_med":"8.0","nt_00":"0.0","ti_max":"12.2","n_nie":"0.0","tm_mes":"11.0","tm_max":"15.9","nv_0100":"0.0","q_min":"1000.6(01)","np_010":"2.0"},{"fecha":"2014-13","indicativo":"5783","p_max":"63.2(27/sep)","n_cub":"51.0","hr":"60.0","n_gra":"0.0","n_fog":"25.0","inso":"9.0","q_max":"1030.4(31/dic)","nw_55":"20.0","q_mar":"1016.4","q_med":"1012.8","tm_min":"13.5","ta_max":"40.6(16/jul)","ts_min":"23.5","nt_30":"124.0","nv_0050":"0.0","n_des":"126.0","w_racha":"27/27.8(09/feb)","np_100":"17.0","n_nub":"187.0","p_sol":"72.0","nw_91":"1.0","np_001":"83.0","ta_min":"2.2(02/feb)","w_rec":"243.0","e":"136.0","np_300":"4.0","nv_1000":"6.0","evap":"22535.0","p_mes":"634.5","n_llu":"95.0","n_tor":"7.0","w_med":"11.0","nt_00":"0.0","ti_max":"11.8","n_nie":"0.0","tm_mes":"19.5","tm_max":"25.6","nv_0100":"0.0","q_min":"977.6(28/nov)","np_010":"59.0"}]
