[{"fecha":"2022-1","indicativo":"9208E","p_max":"53.2(09)","n_cub":"6.0","hr":"45.0","n_gra":"0.0","n_fog":"0.0","inso":"7.2","q_max":"915.4(29)","nw_55":"5.0","q_mar":"1028.4","q_med":"907.0","tm_min":"0.5","ta_max":"19.7(01)","ts_min":"9.9","nt_30":"0.0","nv_0050":"0.0","n_des":"16.0","w_racha":"04/22.5(31)","np_100":"2.0","n_nub":"9.0","p_sol":"76.0","nw_91":"0.0","np_001":"4.0","ta_min":"-5.5(06)","w_rec":"181.0","e":"41.0","np_300":"1.0","nv_1000":"0.0","p_mes":"82.8","n_llu":"3.0","n_tor":"0.0","w_med":"9.0","nt_00":"16.0","ti_max":"5.0","n_nie":"1.0","tm_mes":"6.3","tm_max":"12.1","nv_0100":"0.0","q_min":"891.1(04)","np_010":"4.0"},{"fecha":"2022-2","indicativo":"9208E","p_max":"12.8(13)","n_cub":"4.0","hr":"53.0","n_gra":"0.0","n_fog":"1.0","inso":"7.0","q_max":"912.5(08)","nw_55":"4.0","q_mar":"1025.7","q_med":"905.5","tm_min":"2.0","ta_max":"20.5(02)","ts_min":"6.2","nt_30":"0.0","nv_0050":"0.0","n_des":"7.0","w_racha":"02/20.8(01)","np_100":"1.0","n_nub":"17.0","p_sol":"66.0","nw_91":"0.0","np_001":"2.0","ta_min":"-2.3(06)","w_rec":"180.0","e":"55.0","np_300":"0.0","nv_1000":"0.0","p_mes":"21.8","n_llu":"0.0","n_tor":"0.0","w_med":"9.0","nt_00":"5.0","ti_max":"6.7","n_nie":"2.0","tm_mes":"7.9","tm_max":"13.8","nv_0100":"0.0","q_min":"894.0(14)","np_010":"2.0"},{"fecha":"2022-3","indicativo":"9208E","p_max":"25.0(11)","n_cub":"16.0","hr":"63.0","n_gra":"0.0","n_fog":"4.0","inso":"3.7","q_max":"908.5(18)","nw_55":"5.0","q_mar":"1019.9","q_med":"900.3","tm_min":"3.3","ta_max":"18.8(15)","ts_min":"12.9","nt_30":"0.0","nv_0050":"0.0","n_des":"0.0","w_racha":"99/18.9(15)","np_100":"3.0","n_nub":"15.0","p_sol":"31.0","nw_91":"0.0","np_001":"14.0","ta_min":"-1.2(07)","w_rec":"240.0","e":"64.0","np_300":"0.0","nv_1000":"0.0","p_mes":"72.4","n_llu":"12.0","n_tor":"0.0","w_med":"10.0","nt_00":"4.0","ti_max":"5.2","n_nie":"2.0","tm_mes":"7.6","tm_max":"11.8","nv_0100":"0.0","q_min":"883.9(30)","np_010":"12.0"},{"fecha":"2022-4","indicativo":"9208E","p_max":"40.2(23)","n_cub":"10.0","hr":"56.0","inso":"7.5","q_max":"908.0(28)","nw_55":"6.0","q_mar":"1014.4","q_med":"896.5","tm_min":"3.7","ta_max":"23.4(16)","ts_min":"9.7","nt_30":"0.0","nv_0050":"0.0","n_des":"2.0","w_racha":"35/21.1(02)","np_100":"4.0","n_nub":"15.0","p_sol":"56.0","nw_91":"0.0","np_001":"12.0","ta_min":"-5.5(04)","w_rec":"212.0","e":"71.0","np_300":"1.0","nv_1000":"0.0","p_mes":"137.2","w_med":"10.0","nt_00":"5.0","ti_max":"2.7","tm_mes":"9.4","tm_max":"15.1","nv_0100":"0.0","q_min":"878.7(23)","np_010":"8.0"},{"fecha":"2022-5","indicativo":"9208E","p_max":"7.0(02)","n_cub":"10.0","hr":"43.0","n_gra":"0.0","n_fog":"2.0","inso":"8.9","q_max":"908.8(20)","nw_55":"3.0","q_mar":"1016.5","q_med":"901.6","tm_min":"11.0","ta_max":"32.4(21)","ts_min":"19.0","nt_30":"1.0","nv_0050":"0.0","n_des":"3.0","w_racha":"02/17.8(25)","np_100":"0.0","n_nub":"18.0","p_sol":"60.0","nw_91":"0.0","np_001":"7.0","ta_min":"4.8(05)","w_rec":"253.0","e":"87.0","np_300":"0.0","nv_1000":"0.0","p_mes":"18.8","n_llu":"7.0","n_tor":"3.0","w_med":"12.0","nt_00":"0.0","ti_max":"12.2","n_nie":"0.0","tm_mes":"17.0","tm_max":"23.0","nv_0100":"0.0","q_min":"890.6(29)","np_010":"5.0"},{"fecha":"2022-6","indicativo":"9208E","p_max":"13.4(21)","n_cub":"12.0","hr":"40.0","inso":"8.2","q_max":"910.3(11)","nw_55":"5.0","q_mar":"1013.5","q_med":"900.7","tm_min":"14.9","ta_max":"36.2(17)","ts_min":"23.1","nt_30":"9.0","nv_0050":"0.0","n_des":"5.0","w_racha":"18/23.3(03)","np_100":"1.0","n_nub":"13.0","p_sol":"54.0","nw_91":"0.0","np_001":"8.0","ta_min":"8.6(30)","w_rec":"240.0","e":"106.0","np_300":"0.0","nv_1000":"0.0","p_mes":"26.2","w_med":"10.0","nt_00":"0.0","ti_max":"21.4","tm_mes":"21.4","tm_max":"27.9","nv_0100":"0.0","q_min":"893.7(19)","np_010":"5.0"},{"fecha":"2022-7","indicativo":"9208E","p_max":"16.4(19)","n_cub":"3.0","hr":"36.0","inso":"10.7","q_max":"908.9(07)","nw_55":"2.0","q_mar":"1015.7","q_med":"903.8","tm_min":"16.2","ta_max":"37.8(17)","ts_min":"23.1","nt_30":"24.0","n_des":"18.0","w_racha":"03/19.2(07)","np_100":"1.0","n_nub":"10.0","p_sol":"71.0","nw_91":"0.0","np_001":"6.0","ta_min":"6.4(01)","w_rec":"212.0","e":"113.0","np_300":"0.0","p_mes":"50.4","w_med":"10.0","nt_00":"0.0","ti_max":"19.8","tm_mes":"24.1","tm_max":"31.9","q_min":"898.1(27)","np_010":"6.0"},{"fecha":"2022-8","indicativo":"9208E","p_max":"37.0(29)","n_cub":"0.0","hr":"39.0","n_gra":"0.0","n_fog":"0.0","inso":"9.4","q_max":"906.1(09)","nw_55":"3.0","q_mar":"1013.1","q_med":"900.9","tm_min":"16.1","ta_max":"35.6(12)","ts_min":"21.9","nt_30":"18.0","nv_0050":"0.0","n_des":"8.0","w_racha":"30/26.4(29)","np_100":"1.0","n_nub":"23.0","p_sol":"67.0","nw_91":"1.0","np_001":"8.0","ta_min":"10.0(19)","w_rec":"211.0","e":"115.0","np_300":"1.0","nv_1000":"0.0","p_mes":"55.4","n_llu":"8.0","n_tor":"9.0","w_med":"10.0","nt_00":"0.0","ti_max":"20.9","n_nie":"0.0","tm_mes":"23.5","tm_max":"31.0","nv_0100":"0.0","q_min":"893.1(16)","np_010":"6.0"},{"fecha":"2022-9","indicativo":"9208E"},{"fecha":"2022-10","indicativo":"9208E"},{"fecha":"2022-11","indicativo":"9208E"},{"fecha":"2022-12","indicativo":"9208E"},{"fecha":"2022-13","indicativo":"9208E"}]
